{"skeleton":{"hash":"8PTYiviybGvlB4KTzfiTCMVPbUE","spine":"3.6.53","width":383,"height":490,"images":"./images/"},"bones":[{"name":"root"},{"name":"zong","parent":"root"},{"name":"beike2","parent":"zong","length":45.23,"rotation":80.22,"x":56.59,"y":-44.62},{"name":"bone","parent":"zong","length":182.68,"rotation":129.33,"x":12.92,"y":24.39},{"name":"shanhu1","parent":"zong","length":13.61,"rotation":109.57,"x":-79.2,"y":-114.85},{"name":"bone2","parent":"shanhu1","length":15.86,"rotation":-1.79,"x":13.61},{"name":"bone3","parent":"bone2","length":13.35,"rotation":-1.67,"x":15.86},{"name":"bone4","parent":"bone3","length":9.55,"rotation":1.24,"x":13.35},{"name":"bone5","parent":"bone","length":59.19,"rotation":-105.08,"x":-3.36,"y":-1.51},{"name":"bone6","parent":"bone5","length":45.15,"rotation":3.49,"x":59.19},{"name":"bone7","parent":"bone6","length":33.82,"rotation":28.19,"x":45.15},{"name":"bone8","parent":"bone7","length":23.87,"rotation":12.83,"x":33.82},{"name":"bone9","parent":"bone8","length":24.32,"rotation":60.06,"x":26.9,"y":4.71},{"name":"bone10","parent":"bone9","length":18.54,"rotation":-40.08,"x":25.29,"y":-0.77},{"name":"bone11","parent":"bone8","length":20.2,"rotation":-71.09,"x":25.88,"y":-6.29},{"name":"bone12","parent":"bone11","length":30.11,"rotation":19.04,"x":20.2},{"name":"bone13","parent":"bone","length":60.94,"rotation":-171.86,"x":26.25,"y":-60.92},{"name":"bone14","parent":"bone13","length":51.02,"rotation":-9.02,"x":60.94},{"name":"bone15","parent":"bone14","length":38.15,"rotation":23.88,"x":51.02},{"name":"bone16","parent":"bone15","length":46.01,"rotation":11.02,"x":38.15},{"name":"bone17","parent":"bone","length":40.42,"rotation":84.82,"x":74.16,"y":44.08},{"name":"bone18","parent":"bone17","length":43.26,"rotation":9.06,"x":40.42},{"name":"bone19","parent":"bone18","length":47.66,"rotation":18.38,"x":43.26},{"name":"bone20","parent":"zong","length":19.72,"rotation":122.01,"x":-83.81,"y":-72.82},{"name":"bone21","parent":"zong","length":19.72,"rotation":122.01,"x":-72.1,"y":-83.27},{"name":"bone22","parent":"zong","length":19.72,"rotation":122.01,"x":-62.91,"y":-87.45},{"name":"bone23","parent":"zong","length":19.72,"rotation":122.01,"x":-81.3,"y":-93.31},{"name":"bone24","parent":"zong","length":19.57,"rotation":103.67,"x":-2.22,"y":-79.71},{"name":"bone25","parent":"zong","length":21.33,"rotation":89.31,"x":-29.72,"y":-83.57},{"name":"bone26","parent":"zong","length":17.27,"rotation":85.73,"x":-80.34,"y":-86.4},{"name":"bone27","parent":"zong","length":20.82,"rotation":90,"x":-102.7,"y":-87.42},{"name":"bone28","parent":"zong","length":52.08,"rotation":3.39,"x":17.72,"y":-77.99},{"name":"bone29","parent":"bone","length":72.8,"rotation":-39.33,"x":187.04,"y":7.72,"scaleX":0.493,"scaleY":0.328},{"name":"bone30","parent":"bone","length":72.8,"rotation":-39.33,"x":112.67,"y":-83.06,"scaleX":0.493,"scaleY":0.328},{"name":"bone31","parent":"bone","length":72.8,"rotation":-39.33,"x":83.94,"y":-88.6,"scaleX":0.493,"scaleY":0.328},{"name":"bone32","parent":"bone","length":72.8,"rotation":-39.33,"x":138.69,"y":-66.51,"scaleX":0.493,"scaleY":0.328},{"name":"bone33","parent":"bone","length":72.8,"rotation":-39.33,"x":64.5,"y":-95.64,"scaleX":0.493,"scaleY":0.328},{"name":"shanhu2","parent":"zong","length":80.85,"rotation":112.05,"x":-86.73,"y":-114.94}],"slots":[{"name":"shenhaijujing_tanshi","bone":"zong","attachment":"shenhaijujing_tanshi"},{"name":"shenhaijujing_pp","bone":"bone20","attachment":"shenhaijujing_pp"},{"name":"shenhaijujing_pp4","bone":"bone23","attachment":"shenhaijujing_pp"},{"name":"shenhaijujing_pp2","bone":"bone21","attachment":"shenhaijujing_pp"},{"name":"shenhaijujing_pp3","bone":"bone22","attachment":"shenhaijujing_pp"},{"name":"shenhaijujing_beikegai","bone":"beike2","attachment":"shenhaijujing_beikegai"},{"name":"shenhaijujing_beike","bone":"zong","attachment":"shenhaijujing_beike"},{"name":"shenhaijujing_shanhuhou","bone":"shanhu2","attachment":"shenhaijujing_shanhuhou"},{"name":"shenhaijujing_jinbi","bone":"zong","attachment":"shenhaijujing_jinbi"},{"name":"shenhaijujing_jb5","bone":"root","attachment":"shenhaijujing_jb5"},{"name":"shenhaijujing_shanhu","bone":"shanhu1","attachment":"shenhaijujing_shanhu"},{"name":"shenhaijujing_qi2","bone":"bone17","attachment":"shenhaijujing_qi2"},{"name":"shenhaijujing_shenti","bone":"bone","attachment":"shenhaijujing_shenti"},{"name":"shenhaijujing_qi1","bone":"bone13","attachment":"shenhaijujing_qi1"},{"name":"shenhaijujing_biaoti","bone":"zong","attachment":"shenhaijujing_biaoti"},{"name":"shenhaijujing_jb1","bone":"bone24","attachment":"shenhaijujing_jb1"},{"name":"shenhaijujing_jb2","bone":"bone27","attachment":"shenhaijujing_jb2"},{"name":"shenhaijujing_jb3","bone":"bone26","attachment":"shenhaijujing_jb3"},{"name":"shenhaijujing_jb4","bone":"bone25","attachment":"shenhaijujing_jb4"},{"name":"shenhaijujin_0003","bone":"bone28","attachment":"shenhaijujin_0003","blend":"additive"},{"name":"H5_shenhaijujing_gg1","bone":"bone29","attachment":"H5_shenhaijujing_gg1","blend":"additive"},{"name":"H5_shenhaijujing_gg2","bone":"bone30","attachment":"H5_shenhaijujing_gg1","blend":"additive"},{"name":"H5_shenhaijujing_gg3","bone":"bone31","attachment":"H5_shenhaijujing_gg1","blend":"additive"},{"name":"H5_shenhaijujing_gg4","bone":"bone32","attachment":"H5_shenhaijujing_gg1","blend":"additive"},{"name":"H5_shenhaijujing_gg5","bone":"bone33","attachment":"H5_shenhaijujing_gg1","blend":"additive"}],"skins":{"default":{"H5_shenhaijujing_gg1":{"H5_shenhaijujing_gg1":{"type":"mesh","uvs":[0,1,0.51392,1,1,1,1,0.49922,1,0,0.49178,0,0,0,0,0.50168,0.48383,0.4916],"triangles":[8,6,5,5,4,3,8,5,3,7,6,8,0,7,8,1,8,3,0,8,1,1,3,2],"vertices":[-17.16,-29.71,4.11,-29.71,24.23,-29.71,24.23,0.26,24.23,30.14,3.19,30.14,-17.16,30.14,-17.16,0.11,2.86,0.72],"hull":8,"edges":[0,2,2,4,4,6,6,8,8,10,10,12,12,14,0,14],"width":50,"height":50}},"H5_shenhaijujing_gg2":{"H5_shenhaijujing_gg1":{"type":"mesh","uvs":[0,1,0.51392,1,1,1,1,0.49922,1,0,0.49178,0,0,0,0,0.50168,0.48383,0.4916],"triangles":[8,6,5,5,4,3,8,5,3,7,6,8,0,7,8,1,8,3,0,8,1,1,3,2],"vertices":[-17.16,-29.71,4.11,-29.71,24.23,-29.71,24.23,0.26,24.23,30.14,3.19,30.14,-17.16,30.14,-17.16,0.11,2.86,0.72],"hull":8,"edges":[0,2,2,4,4,6,6,8,8,10,10,12,12,14,0,14],"width":50,"height":50}},"H5_shenhaijujing_gg3":{"H5_shenhaijujing_gg1":{"type":"mesh","uvs":[0,1,0.51392,1,1,1,1,0.49922,1,0,0.49178,0,0,0,0,0.50168,0.48383,0.4916],"triangles":[8,6,5,5,4,3,8,5,3,7,6,8,0,7,8,1,8,3,0,8,1,1,3,2],"vertices":[-17.16,-29.71,4.11,-29.71,24.23,-29.71,24.23,0.26,24.23,30.14,3.19,30.14,-17.16,30.14,-17.16,0.11,2.86,0.72],"hull":8,"edges":[0,2,2,4,4,6,6,8,8,10,10,12,12,14,0,14],"width":50,"height":50}},"H5_shenhaijujing_gg4":{"H5_shenhaijujing_gg1":{"type":"mesh","uvs":[0,1,0.51392,1,1,1,1,0.49922,1,0,0.49178,0,0,0,0,0.50168,0.48383,0.4916],"triangles":[8,6,5,5,4,3,8,5,3,7,6,8,0,7,8,1,8,3,0,8,1,1,3,2],"vertices":[-17.16,-29.71,4.11,-29.71,24.23,-29.71,24.23,0.26,24.23,30.14,3.19,30.14,-17.16,30.14,-17.16,0.11,2.86,0.72],"hull":8,"edges":[0,2,2,4,4,6,6,8,8,10,10,12,12,14,0,14],"width":50,"height":50}},"H5_shenhaijujing_gg5":{"H5_shenhaijujing_gg1":{"type":"mesh","uvs":[0,1,0.51392,1,1,1,1,0.49922,1,0,0.49178,0,0,0,0,0.50168,0.48383,0.4916],"triangles":[8,6,5,5,4,3,8,5,3,7,6,8,0,7,8,1,8,3,0,8,1,1,3,2],"vertices":[-17.16,-29.71,4.11,-29.71,24.23,-29.71,24.23,0.26,24.23,30.14,3.19,30.14,-17.16,30.14,-17.16,0.11,2.86,0.72],"hull":8,"edges":[0,2,2,4,4,6,6,8,8,10,10,12,12,14,0,14],"width":50,"height":50}},"shenhaijujin_0003":{"shenhaijujin_0003":{"x":35.03,"y":3.64,"rotation":-3.39,"width":80,"height":85},"shenhaijujin_0004":{"x":35.03,"y":3.64,"rotation":-3.39,"width":80,"height":85},"shenhaijujin_0005":{"x":35.03,"y":3.64,"rotation":-3.39,"width":80,"height":85},"shenhaijujin_0006":{"x":35.03,"y":3.64,"rotation":-3.39,"width":80,"height":85},"shenhaijujin_0007":{"x":35.03,"y":3.64,"rotation":-3.39,"width":80,"height":85},"shenhaijujin_0008":{"x":35.03,"y":3.64,"rotation":-3.39,"width":80,"height":85},"shenhaijujin_0009":{"x":35.03,"y":3.64,"rotation":-3.39,"width":80,"height":85},"shenhaijujin_0010":{"x":35.03,"y":3.64,"rotation":-3.39,"width":80,"height":85},"shenhaijujin_0011":{"x":35.03,"y":3.64,"rotation":-3.39,"width":80,"height":85},"shenhaijujin_0012":{"x":35.03,"y":3.64,"rotation":-3.39,"width":80,"height":85},"shenhaijujin_0013":{"x":35.03,"y":3.64,"rotation":-3.39,"width":80,"height":85},"shenhaijujin_0014":{"x":35.03,"y":3.64,"rotation":-3.39,"width":80,"height":85},"shenhaijujin_0015":{"x":35.03,"y":3.64,"rotation":-3.39,"width":80,"height":85},"shenhaijujin_0016":{"x":35.03,"y":3.64,"rotation":-3.39,"width":80,"height":85},"shenhaijujin_0017":{"x":35.03,"y":3.64,"rotation":-3.39,"width":80,"height":85}},"shenhaijujing_beike":{"shenhaijujing_beike":{"x":34.05,"y":-77.38,"width":165,"height":77}},"shenhaijujing_beikegai":{"shenhaijujing_beikegai":{"x":35.09,"y":5.31,"rotation":-80.22,"width":166,"height":121}},"shenhaijujing_biaoti":{"shenhaijujing_biaoti":{"x":2.55,"y":-102.88,"width":344,"height":294}},"shenhaijujing_jb1":{"shenhaijujing_jb1":{"x":8.6,"y":0.59,"rotation":-103.67,"width":28,"height":23}},"shenhaijujing_jb2":{"shenhaijujing_jb2":{"x":7.9,"y":-0.06,"rotation":-90,"width":28,"height":23}},"shenhaijujing_jb3":{"shenhaijujing_jb3":{"x":7.76,"y":-1.78,"rotation":-85.73,"width":19,"height":19}},"shenhaijujing_jb4":{"shenhaijujing_jb4":{"x":10.61,"y":0.33,"rotation":-89.31,"width":21,"height":25}},"shenhaijujing_jb5":{"shenhaijujing_jb5":{"x":-29,"y":-72.95,"width":77,"height":55}},"shenhaijujing_jinbi":{"shenhaijujing_jinbi":{"x":55.34,"y":-72.88,"width":117,"height":85}},"shenhaijujing_pp":{"shenhaijujing_pp":{"x":8.11,"y":2.06,"scaleX":0.5,"scaleY":0.5,"rotation":-122.01,"width":38,"height":38}},"shenhaijujing_pp2":{"shenhaijujing_pp":{"x":8.11,"y":2.06,"scaleX":0.5,"scaleY":0.5,"rotation":-122.01,"width":38,"height":38}},"shenhaijujing_pp3":{"shenhaijujing_pp":{"x":8.11,"y":2.06,"scaleX":0.5,"scaleY":0.5,"rotation":-122.01,"width":38,"height":38}},"shenhaijujing_pp4":{"shenhaijujing_pp":{"x":8.11,"y":2.06,"scaleX":0.5,"scaleY":0.5,"rotation":-122.01,"width":38,"height":38}},"shenhaijujing_qi1":{"shenhaijujing_qi1":{"type":"mesh","uvs":[0,0.04897,0.04565,0.13493,0.08847,0.21032,0.13858,0.30951,0.17138,0.41135,0.20691,0.5489,0.22696,0.63487,0.25338,0.73274,0.29438,0.77638,0.33447,0.77506,0.37,0.76051,0.44836,0.85177,0.50576,0.88219,0.54767,0.88219,0.58229,0.86632,0.63422,0.9298,0.70711,0.98271,0.76907,0.99593,0.83558,0.99064,0.88113,0.98932,0.94491,1,0.98956,1,1,0.97477,1,0.91922,0.96678,0.87954,0.90391,0.83325,0.85745,0.8068,0.80278,0.7658,0.75176,0.72348,0.70894,0.68909,0.65518,0.62958,0.58958,0.58461,0.52307,0.50922,0.45109,0.41532,0.39551,0.33729,0.33265,0.24735,0.27251,0.17461,0.20327,0.09922,0.14951,0.04764,0.08574,0,0.0338,0,0.0092,0,0,0.02119,0.65818,0.86283,0.67651,0.77962,0.72766,0.86172,0.51009,0.65211,0.45431,0.71196,0.34396,0.3511,0.27241,0.38807,0.32334,0.48136,0.39368,0.60106,0.23967,0.25781],"triangles":[21,20,22,22,20,23,18,17,45,17,16,45,18,45,26,19,18,25,26,45,27,24,23,20,19,25,24,25,18,26,16,15,45,45,15,43,20,19,24,43,44,45,27,44,28,27,45,44,44,29,28,15,14,43,13,12,14,14,12,47,43,14,44,14,46,44,11,47,12,46,14,47,44,46,30,46,31,30,44,30,29,46,32,31,11,10,47,8,7,9,9,7,10,47,10,51,10,7,51,7,6,51,47,51,46,46,51,32,6,50,51,6,5,50,51,33,32,51,50,33,5,49,50,50,48,33,48,34,33,50,49,48,48,35,34,5,4,49,4,3,49,3,52,49,49,52,48,52,35,48,3,2,52,52,36,35,36,52,37,52,2,37,37,1,38,37,2,1,39,1,0,40,42,41,1,39,38,39,0,40,40,0,42],"vertices":[2,16,-5.74,-8.32,1,19,-142.92,58.11,0,1,16,7.52,-10.62,1,2,16,19.52,-12.3,1,19,-121.93,43.51,0,3,16,34.48,-15.27,0.98548,17,-23.74,-19.23,0.01452,19,-109.76,34.31,0,3,16,47.37,-20.58,0.75468,17,-10.18,-22.46,0.24532,19,-100.49,23.9,0,3,16,63.61,-28.83,0.20261,17,7.16,-28.05,0.79739,19,-89.47,9.39,0,3,16,73.48,-34.24,0.04907,17,17.75,-31.85,0.95093,19,-82.96,0.21,0,4,16,85.19,-39.97,0.00307,17,30.21,-35.67,0.99609,18,-33.48,-24.19,8.4E-4,19,-74.93,-10.05,0,3,17,39.04,-33.26,0.98703,18,-24.43,-25.56,0.01297,19,-66.31,-13.12,0,3,17,43.39,-27.5,0.95463,18,-18.11,-22.06,0.04537,19,-59.44,-10.9,0,3,17,45.96,-21.37,0.84906,18,-13.29,-17.49,0.15094,19,-53.83,-7.33,0,3,17,63.59,-17.36,0.24044,18,4.46,-20.96,0.75956,19,-37.07,-14.14,0,2,17,72.97,-11.61,0.04651,18,15.36,-19.5,0.95349,2,17,77.66,-5.71,0.00397,18,22.04,-16,0.99603,2,18,26.65,-11.36,0.95975,19,-13.46,-8.96,0.04025,2,18,38.58,-13.99,0.49286,19,-2.25,-13.82,0.50714,2,18,53.25,-13.71,0.04773,19,12.2,-16.34,0.95227,1,19,23.36,-14.72,1,1,19,34.64,-10.66,1,1,19,42.45,-8.16,1,1,19,53.83,-6.14,1,2,18,99.27,8,0,19,61.52,-3.83,1,2,18,99.48,11.64,0,19,62.43,-0.3,1,2,18,96.28,17.74,0,19,60.46,6.3,1,2,18,88.7,19.32,0,19,53.32,9.3,1,2,18,76.01,19.15,1.0E-5,19,40.83,11.56,0.99999,1,19,31.88,12.31,1,2,18,56.01,18.11,0.01074,19,20.99,14.36,0.98926,2,18,45.44,18.49,0.20985,19,10.69,16.75,0.79015,2,18,36.63,18.69,0.55291,19,2.08,18.63,0.44709,3,17,65.16,28.93,0.02037,18,24.63,20.73,0.87699,19,-9.3,22.93,0.10263,3,17,53.45,23.15,0.21428,18,11.59,20.18,0.78282,19,-22.21,24.89,0.00289,3,17,38.68,19.58,0.76614,18,-3.36,22.9,0.23385,19,-36.36,30.41,1.0E-5,4,16,84.8,13.09,1.4E-4,17,21.51,16.67,0.99634,18,-20.24,27.2,0.00352,19,-52.11,37.86,0,3,16,70.89,13.46,0.16133,17,7.71,14.85,0.83867,19,-64.47,44.26,0,3,16,55.01,14.03,0.78089,17,-8.06,12.92,0.21911,19,-78.5,51.7,0,1,16,40.94,13.36,1,1,16,25.43,11.82,1,1,16,13.98,9.99,1,2,16,1.53,6.58,1,19,-129.87,68.35,0,1,16,-5.36,0.26,1,2,16,-8.63,-2.73,1,19,-143.07,64.41,0,2,16,-8.07,-5.79,1,19,-143.9,61.41,0,2,18,38.54,-4.64,0.65521,19,-0.5,-4.63,0.34479,2,18,36.68,6.03,0.71718,19,-0.29,6.2,0.28282,1,19,11.45,-0.91,1,2,17,51.11,6.73,0.39943,18,2.8,6.12,0.60057,3,17,50.68,-5.74,0.57603,18,-2.64,-5.11,0.42397,19,-41.01,2.78,0,3,16,65.21,5.92,0.31091,17,3.28,6.52,0.68909,19,-72.87,39.96,0,2,16,58.82,-6.16,0.69815,17,-1.13,-6.42,0.30185,1,17,13.63,-6.43,1,1,17,33.12,-5.74,1,1,16,43.55,1.76,1],"hull":43,"edges":[0,2,2,4,4,6,6,8,8,10,10,12,12,14,14,16,16,18,18,20,20,22,22,24,24,26,26,28,28,30,30,32,32,34,34,36,36,38,38,40,40,42,42,44,44,46,46,48,48,50,50,52,52,54,54,56,56,58,58,60,60,62,62,64,64,66,66,68,68,70,70,72,72,74,74,76,76,78,78,80,80,82,82,84,0,84],"width":180,"height":124}},"shenhaijujing_qi2":{"shenhaijujing_qi2":{"type":"mesh","uvs":[0.99458,0.11987,0.94922,0.23078,0.82447,0.37305,0.71674,0.44056,0.5608,0.56112,0.48709,0.59247,0.4559,0.6648,0.39636,0.70097,0.30564,0.74196,0.25461,0.81912,0.16388,0.92521,0.093,0.99755,0.00511,1,0,0.90833,0,0.79018,0,0.71785,0.05898,0.65033,0.12135,0.58764,0.12419,0.47432,0.17806,0.41886,0.25744,0.25007,0.36518,0.15845,0.51544,0.09335,0.65153,0.04512,0.79896,0.01136,0.92087,0,0.98608,0.03548,0.68272,0.28624,0.61184,0.20908,0.46441,0.3851,0.351,0.47914,0.27445,0.55148,0.22909,0.52736,0.19507,0.67204],"triangles":[12,13,11,11,13,10,9,14,33,14,9,10,33,14,16,14,10,13,9,33,8,14,15,16,7,8,31,8,33,31,7,31,6,16,17,33,33,32,31,33,17,32,17,18,32,6,31,5,5,31,30,4,5,29,5,30,29,4,29,3,31,32,30,18,19,32,32,19,30,29,30,20,29,27,3,30,19,20,20,21,29,29,28,27,28,21,22,28,29,21,3,27,2,2,27,1,27,24,1,1,24,0,28,23,27,27,23,24,0,25,26,25,0,24,28,22,23],"vertices":[1,20,4.03,6.36,1,2,20,14.1,13.86,0.99921,21,-23.81,17.83,7.9E-4,2,20,32.04,20.09,0.74939,21,-5.12,21.16,0.25061,2,20,44.21,20.56,0.29871,21,6.98,19.71,0.70129,3,20,63.2,23.28,0.00127,21,26.15,19.4,0.97646,22,-10.12,23.81,0.02227,2,21,33.34,17.26,0.83744,22,-3.97,19.5,0.16256,2,21,40.7,20.96,0.50726,22,4.18,20.69,0.49274,2,21,47.3,20.07,0.29107,22,10.17,17.77,0.70893,2,21,56.32,17.61,0.03923,22,17.95,12.6,0.96077,1,22,27.42,12.44,1,1,22,41.34,10.59,1,1,22,51.21,8.6,1,1,22,55.25,1.69,1,1,22,46.85,-3.39,1,1,22,35.73,-9.41,1,1,22,28.92,-13.09,1,1,22,20.02,-11.81,1,2,21,57.25,-5.9,0.03791,22,11.41,-10.01,0.96209,2,21,48.76,-14.57,0.43919,22,0.63,-15.56,0.56081,2,21,41.12,-15.54,0.72828,22,-6.92,-14.07,0.27172,3,20,67.36,-19.76,0.00274,21,23.49,-23.76,0.99499,22,-26.25,-16.31,0.00227,2,20,53.75,-22.37,0.09105,21,9.63,-24.19,0.90895,2,20,38.52,-20.46,0.5352,21,-5.1,-19.91,0.4648,2,20,25.37,-17.78,0.93411,21,-17.66,-15.19,0.06589,1,20,12.24,-13.24,1,1,20,2.38,-8.02,1,1,20,-0.4,-1.55,1,2,20,37.51,5.16,0.64701,21,-2.07,5.56,0.35299,2,20,38.21,-5.29,0.79474,21,-3.02,-4.88,0.20526,1,21,19.65,-0.33,1,1,21,34.06,-0.06,1,2,21,44.44,0.81,0.36758,22,1.38,0.4,0.63242,2,21,45.68,-3.89,0.34929,22,1.08,-4.46,0.65071,1,22,16.16,0.19,1],"hull":27,"edges":[0,2,2,4,4,6,6,8,8,10,10,12,12,14,14,16,16,18,18,20,20,22,22,24,24,26,26,28,28,30,30,32,32,34,34,36,36,38,38,40,40,42,42,44,44,46,46,48,48,50,50,52,0,52],"width":91,"height":107}},"shenhaijujing_shanhu":{"shenhaijujing_shanhu":{"type":"mesh","uvs":[0.55325,1,0.35385,0.82199,0.20004,0.6531,0.10319,0.46192,0.02343,0.31216,0,0.16877,0,0.0668,0.14876,0,0.38804,0,0.54755,0.02856,0.58173,0.1146,0.63301,0.24843,0.66149,0.38863,0.76404,0.58619,0.84379,0.74232,1,0.95263,1,1,0.82101,1,0.25131,0.14328,0.33107,0.3026,0.4621,0.5607,0.58743,0.78693],"triangles":[18,7,8,5,6,7,5,7,18,19,18,8,10,19,8,4,5,18,4,18,19,9,10,8,11,19,10,3,4,19,20,19,12,12,19,11,3,19,20,20,12,13,2,3,20,21,20,13,21,13,14,1,2,20,1,20,21,0,1,21,17,21,14,17,14,15,0,21,17,17,15,16],"vertices":[1,4,1.37,6.94,1,2,4,13.47,9.62,0.44746,5,-0.44,9.61,0.55254,3,4,24.56,11.06,0.00361,5,10.6,11.4,0.84735,6,-5.59,11.24,0.14905,3,5,22.32,11,0.14894,6,6.13,11.18,0.75589,7,-6.98,11.33,0.09518,3,5,31.53,10.8,0.00119,6,15.35,11.26,0.3796,7,2.24,11.21,0.61921,2,6,23.69,9.65,0.02669,7,10.55,9.42,0.97331,1,7,16.29,7.63,1,2,6,31.89,2.17,3.0E-5,7,18.59,1.77,0.99997,1,7,16.23,-5.77,1,2,6,26.62,-10,5.1E-4,7,13.05,-10.29,0.99949,2,6,21.43,-9.68,0.04657,7,7.87,-9.85,0.95343,2,6,13.38,-9.11,0.52367,7,-0.17,-9.11,0.47633,3,5,20.81,-7.87,0.07632,6,5.17,-7.72,0.90973,7,-8.34,-7.54,0.01395,3,4,22.05,-7.8,0.00515,5,8.67,-7.53,0.9613,6,-6.97,-7.74,0.03355,2,4,12.48,-7.19,0.59298,5,-0.9,-7.22,0.40702,1,4,-0.93,-7.89,1,1,4,-3.57,-6.96,1,1,4,-1.59,-1.39,1,1,7,9.51,1.06,1,2,6,13.07,1.35,0.43153,7,-0.25,1.35,0.56847,2,5,13.15,1.5,0.91347,6,-2.76,1.42,0.08653,2,4,12.84,1.66,0.74848,5,-0.82,1.64,0.25152],"hull":18,"edges":[0,2,2,4,4,6,6,8,8,10,10,12,12,14,14,16,16,18,18,20,20,22,22,24,24,26,26,28,28,30,30,32,32,34,0,34],"width":33,"height":59}},"shenhaijujing_shanhuhou":{"shenhaijujing_shanhuhou":{"x":43.18,"y":-8.09,"rotation":-112.05,"width":88,"height":86}},"shenhaijujing_shenti":{"shenhaijujing_shenti":{"type":"mesh","uvs":[0,0.51402,0.07487,0.60902,0.10781,0.76011,0.163,0.88601,0.22643,0.97872,0.28573,1,0.41011,1,0.4793,0.98674,0.54462,0.9608,0.60721,0.92257,0.65055,0.88912,0.68838,0.84515,0.72828,0.79831,0.76542,0.75435,0.79225,0.71229,0.80944,0.66928,0.81976,0.63487,0.84452,0.6234,0.86516,0.61384,0.89199,0.61766,0.91744,0.61193,0.94289,0.57943,0.96627,0.53929,0.98416,0.50679,0.99723,0.46569,1,0.43128,0.99585,0.41598,0.98416,0.43032,0.97453,0.44753,0.95389,0.46664,0.93601,0.47429,0.91331,0.47524,0.8913,0.47142,0.86378,0.46282,0.84452,0.46569,0.82939,0.46951,0.82389,0.44275,0.81976,0.41694,0.81013,0.39113,0.79362,0.37966,0.78124,0.36724,0.77986,0.33761,0.78193,0.31371,0.77986,0.28886,0.76336,0.29459,0.75235,0.31945,0.73859,0.34812,0.72552,0.38253,0.72002,0.41694,0.71864,0.44657,0.72208,0.48002,0.73103,0.50296,0.74685,0.52495,0.7551,0.55075,0.75579,0.57465,0.73653,0.5995,0.72346,0.62244,0.70833,0.62149,0.68907,0.60619,0.67531,0.58325,0.65467,0.56031,0.6251,0.54502,0.60308,0.50201,0.6251,0.47047,0.6024,0.41981,0.6134,0.35386,0.55769,0.30989,0.49371,0.21048,0.36717,0.16667,0.23717,0.18483,0.16356,0.15042,0.11541,0,0.08102,0,0.02668,0.18005,0,0.35688,0,0.51364,0.62552,0.59258,0.62271,0.6485,0.6068,0.72783,0.57311,0.80197,0.54784,0.86569,0.49262,0.94633,0.80288,0.49761,0.78692,0.51904,0.8417,0.50574,0.82255,0.54786,0.89275,0.50131,0.89434,0.53678,0.89966,0.57594,0.81723,0.48136,0.78373,0.39194,0.75555,0.40155,0.73959,0.40894,0.77788,0.59072,0.80022,0.61067,0.73374,0.64245,0.7598,0.69861,0.7146,0.64836,0.73427,0.72595,0.76459,0.61658,0.78852,0.63875,0.41716,0.47424,0.43006,0.51993,0.45045,0.54133,0.47501,0.54075,0.48583,0.51935,0.48,0.47945,0.46252,0.44417,0.44129,0.43434,0.42381,0.44301,0.44587,0.45631,0.45535,0.47659,0.44298,0.47697,0.43625,0.48435,0.43864,0.51363,0.45511,0.53065,0.47203,0.52893,0.47724,0.51838,0.47068,0.48911],"triangles":[27,26,25,25,28,27,24,28,25,86,32,31,24,29,28,23,29,24,22,87,86,23,30,29,22,30,23,87,21,88,86,31,30,86,30,22,22,21,87,20,88,21,19,18,88,20,19,88,84,35,34,89,35,84,84,34,33,33,86,84,86,33,32,84,87,85,87,84,86,44,43,42,45,44,42,41,45,42,46,45,41,46,41,40,91,47,46,90,40,39,40,91,46,90,91,40,92,47,91,48,47,92,92,49,48,82,50,49,39,38,90,36,82,37,89,36,35,90,38,37,36,89,82,37,91,90,82,91,37,82,51,50,49,92,91,49,91,82,82,89,84,83,51,82,52,51,83,85,82,84,83,82,85,53,52,83,53,93,54,85,53,83,85,93,53,94,93,85,88,85,87,88,18,85,17,94,85,18,17,85,93,55,54,99,93,94,99,55,93,56,55,99,16,94,17,100,99,94,100,94,16,95,56,99,97,56,95,15,100,16,100,96,95,100,95,99,96,100,15,14,96,15,96,97,95,13,96,14,76,60,59,97,57,56,98,97,96,76,59,58,97,77,58,98,96,13,12,98,13,97,58,57,97,98,78,12,78,98,11,78,12,10,79,11,9,80,10,9,8,80,72,71,70,73,72,70,64,66,65,108,68,67,108,67,66,107,108,66,109,68,108,64,107,66,110,108,107,109,108,110,109,69,68,101,109,110,111,110,107,112,101,110,111,112,110,106,107,64,62,106,64,111,107,106,113,101,112,118,111,106,63,62,64,111,114,113,111,113,112,118,114,111,74,1,75,74,73,70,70,69,74,1,0,75,105,117,118,106,105,118,114,118,117,62,105,106,102,101,113,102,113,114,117,115,114,116,115,117,105,104,116,105,116,117,115,102,114,103,102,115,76,61,60,1,74,101,109,74,69,109,101,74,105,61,76,61,105,62,76,104,105,77,104,76,78,104,77,77,76,58,102,2,1,102,1,101,97,78,77,78,103,104,79,78,11,78,79,103,103,3,2,103,2,102,115,116,104,103,115,104,79,3,103,80,79,10,79,80,3,8,81,80,81,3,80,5,4,3,3,81,5,7,81,8,81,6,5,7,6,81],"vertices":[1,3,168.87,67.68,1,1,3,134.16,62.63,1,1,3,97.83,77.65,1,1,3,61.48,82.75,1,1,3,29.72,80.4,1,2,3,12.61,67.89,0.9941,8,-71.16,-2.63,0.0059,1,3,-14.66,34.6,1,1,3,-27.28,13.98,1,2,3,-36.6,-7.59,0.07406,8,14.52,-30.51,0.92594,2,8,38.18,-30.73,0.89036,9,-22.84,-29.39,0.10964,2,8,55.27,-29.29,0.66205,9,-5.7,-28.99,0.33795,3,8,71.7,-24.68,0.31833,9,10.98,-25.4,0.67685,10,-42.11,-6.24,0.00482,3,8,89.08,-19.72,0.07106,9,28.63,-21.5,0.83916,10,-24.72,-11.14,0.08978,3,8,105.29,-15.01,3.2E-4,9,45.1,-17.79,0.61822,10,-8.45,-15.65,0.38146,3,9,58.19,-12.84,0.26241,10,5.43,-17.48,0.73712,14,-14.42,-55.78,4.7E-4,5,9,68.44,-6.13,0.05072,10,17.63,-16.4,0.8735,11,-19.43,-12.4,0.04663,14,-8.91,-44.84,0.02588,15,-42.15,-32.89,0.00326,5,9,75.59,-0.21,8.2E-4,10,26.73,-14.56,0.65492,11,-10.15,-12.62,0.21772,14,-5.69,-36.13,0.10346,15,-36.27,-25.71,0.02308,4,10,33.9,-20.06,0.33883,11,-4.38,-19.57,0.29599,14,2.75,-32.93,0.27685,15,-27.24,-25.44,0.08833,4,10,39.87,-24.64,0.16376,11,0.42,-25.36,0.29514,14,9.79,-30.26,0.35815,15,-19.72,-25.21,0.18295,4,10,44.28,-32.86,0.09788,11,2.9,-34.36,0.20129,14,19.1,-30.83,0.3345,15,-11.1,-28.79,0.36633,4,10,50.4,-39.35,0.05666,11,7.42,-42.05,0.13796,14,27.84,-29.05,0.30414,15,-2.25,-29.95,0.50124,4,10,62.03,-42.11,0.02007,11,18.16,-47.32,0.068,14,36.31,-20.6,0.21203,15,8.51,-24.73,0.69991,4,10,74.85,-43.21,0.00278,11,30.41,-51.24,0.01881,14,43.99,-10.28,0.04647,15,19.13,-17.48,0.93193,3,11,40.19,-54.08,0.0038,14,49.84,-1.95,2.5E-4,15,27.38,-11.51,0.99596,1,15,34.65,-3,1,3,10,103.66,-37.81,0,14,54.55,17.06,2.7E-4,15,38.03,4.93,0.99973,3,10,106.01,-34.49,0,14,52.96,20.81,2.9E-4,15,37.75,8.99,0.99971,3,10,100.79,-33.14,0,14,49.07,17.08,2.7E-4,15,32.85,6.73,0.99973,3,10,95.37,-32.78,0,14,45.91,12.66,1.8E-4,15,28.43,3.58,0.99982,1,15,20.22,1.08,1,3,10,82.38,-25.47,0,14,32.87,5.46,0.02764,15,13.75,1.03,0.97236,2,14,25.03,4.9,0.31294,15,6.16,3.06,0.68706,2,14,17.38,5.54,0.67297,15,-0.86,6.16,0.32703,2,12,-9.68,-15.26,0.005,14,7.78,7.29,0.995,3,11,32.22,-5.34,0.00235,12,-6.06,-9.62,0.06645,14,1.15,6.31,0.9312,3,11,29.43,-0.8,0.26207,12,-3.52,-4.95,0.51413,14,-4.04,5.14,0.2238,4,11,34.95,3.39,0.0889,12,2.87,-7.64,0.83399,13,-12.73,-19.69,0.0096,14,-6.22,11.72,0.06751,4,11,40.42,7.05,0.01346,12,8.77,-10.55,0.88211,13,-6.34,-18.12,0.09268,14,-7.9,18.09,0.01174,3,12,15.87,-11.99,0.77103,13,0.01,-14.64,0.22881,14,-11.5,24.37,1.6E-4,2,12,21.67,-9.33,0.54987,13,2.74,-8.87,0.45013,2,12,26.77,-7.93,0.23312,13,5.74,-4.52,0.76688,1,13,13.11,-3.88,1,1,13,19.07,-4.46,1,1,13,25.24,-3.61,1,1,13,23.69,2.07,1,2,10,78.71,48.77,3.0E-5,13,17.41,5.74,0.99997,5,10,70.13,48.71,1.3E-4,11,46.22,39.43,0.00363,12,39.73,0.59,0.00866,13,10.17,10.34,0.98757,14,-36.66,34.06,0,4,11,36.59,40.54,0.04043,12,35.88,9.48,0.31585,13,1.5,14.67,0.64343,14,-40.83,25.32,3.0E-4,4,11,27.92,39.21,0.09921,12,30.4,16.34,0.52663,13,-7.1,16.38,0.37314,14,-42.39,16.68,0.00103,5,10,45.96,40.69,0.00392,11,20.87,36.98,0.19077,12,24.95,21.33,0.58365,13,-14.49,16.7,0.21945,14,-42.56,9.29,0.00221,5,10,39.73,35.04,0.01825,11,13.53,32.85,0.30545,12,17.71,25.62,0.58127,13,-22.79,15.32,0.09187,14,-41.03,1.01,0.00317,5,10,36.73,29.27,0.04367,11,9.33,27.9,0.38993,12,11.32,26.79,0.52709,13,-28.43,12.1,0.0363,14,-37.71,-4.57,0.00302,5,10,35.26,21.67,0.1118,11,6.22,20.81,0.51636,12,3.63,25.96,0.36404,13,-33.79,6.51,0.00625,14,-32.02,-9.81,0.00155,3,10,31.54,15.71,0.29404,11,1.26,15.82,0.52979,12,-3.17,27.76,0.17617,5,3,-8.53,-125.04,1.8E-4,9,62.97,23.37,0.0087,10,26.75,12.18,0.55164,11,-4.2,13.44,0.36717,12,-7.96,31.3,0.07232,5,3,-9.09,-115.97,0.00201,9,54.2,20.99,0.12127,10,17.89,14.23,0.72817,11,-12.38,17.41,0.12673,12,-8.6,40.38,0.02183,6,3,-10.64,-108.85,0.00722,8,105.54,20.9,0.00357,9,47.54,18.04,0.34241,10,10.62,14.77,0.61617,11,-19.34,19.56,0.0267,12,-10.22,47.48,0.00392,6,3,-7.14,-104.95,0.01726,8,100.87,23.26,0.01434,9,43.01,20.69,0.52039,10,7.89,19.24,0.43874,11,-21.02,24.52,0.00844,12,-6.75,51.41,8.4E-4,6,3,0.03,-102.21,0.04212,8,96.35,29.47,0.04798,9,38.89,27.16,0.65107,10,7.31,26.9,0.25757,11,-19.89,32.11,0.00123,12,0.39,54.22,4.0E-5,4,3,7.46,-102.15,0.07361,8,94.36,36.64,0.07622,9,37.33,34.43,0.67427,10,9.37,34.04,0.1759,4,3,16.41,-100.24,0.12084,8,90.19,44.78,0.11235,9,33.67,42.81,0.65684,10,10.1,43.15,0.10997,1,3,25.84,-94.74,1,1,3,38.95,-95.64,1,1,3,40.2,-106.5,1,1,3,54.93,-108.42,1,1,3,65.22,-121.78,1,1,3,85.91,-113.8,1,1,3,119.08,-112.37,1,1,3,155.27,-85.41,1,1,3,180.28,-47.75,1,1,3,203.04,-33.48,1,1,3,242.57,-44.33,1,1,3,250.12,-35.12,1,1,3,227.35,7.83,1,1,3,199.14,42.88,1,1,3,168.95,67.61,1,1,3,16.58,-87.35,1,1,3,6.43,-77.77,1,1,3,-5.36,-61,1,1,3,-12.26,-40.28,1,1,3,-18.99,-23.46,1,1,3,-22.41,4.04,1,2,11,19.59,5.21,0.5,12,-3.22,6.59,0.5,3,10,44.25,11.01,0.07103,11,12.61,8.42,0.72603,12,-3.92,14.23,0.20294,1,14,0.58,-3.7,1,1,11,10.39,-5.67,1,2,14,18.18,-1.87,0.5,15,-2.52,-1.11,0.5,4,10,61.42,-22.25,0.01122,11,21.97,-27.82,0.05716,14,19.1,-10.68,0.35966,15,-4.53,-9.73,0.57196,4,10,54.37,-29.24,0.0624,11,13.54,-33.07,0.1462,14,21.33,-20.34,0.32101,15,-5.57,-19.6,0.47039,2,11,25.16,2.05,0.5,12,-3.18,0.18,0.5,2,12,21.43,-4.74,0.54987,13,-0.39,-5.52,0.45013,2,12,25.68,4.36,0.5,13,-3,4.18,0.5,4,11,32.23,33.62,0.06899,12,27.71,9.81,0.56118,13,-4.96,9.66,0.36929,14,-35.7,18.95,5.3E-4,2,10,27.71,3.6,0.5,11,-5.16,4.87,0.5,4,10,27.93,-5.58,0.61128,11,-6.99,-4.13,0.2821,14,-12.69,-30.39,0.09035,15,-41.01,-18,0.01626,3,3,-16.75,-108.45,0.00179,9,48.37,11.97,0.27626,10,8.49,9.04,0.72195,2,9,49.84,-4.6,0.5,10,1.96,-6.27,0.5,3,3,-13.69,-102.39,0.00803,9,41.82,13.75,0.68893,10,3.56,13.7,0.30305,2,9,38.85,-6.52,0.78679,10,-8.63,-2.77,0.21321,1,10,19.8,3.8,1,5,9,65.57,3.97,0.01378,10,19.87,-6.15,0.87102,11,-14.97,-2.9,0.07525,14,-16.45,-37.54,0.03471,15,-46.9,-23.53,0.00524,1,3,85.06,-50.25,1,1,3,73.44,-46.5,1,1,3,64.84,-48.58,1,1,3,59.57,-55.24,1,1,3,61.32,-61.52,1,1,3,70.28,-66.25,1,1,3,80.91,-67.14,1,1,3,87.46,-63.01,1,1,3,89.62,-56.96,1,1,3,82.22,-60.77,1,1,3,76.24,-60.11,1,1,3,78.88,-56.73,1,1,3,78.93,-53.77,1,1,3,72.77,-49.79,1,1,3,65.88,-51.51,1,1,3,62.5,-56.31,1,1,3,63.39,-59.37,1,1,3,70.46,-62.23,1],"hull":76,"edges":[0,2,2,4,4,6,6,8,8,10,10,12,12,14,14,16,16,18,18,20,20,22,22,24,24,26,26,28,28,30,30,32,32,34,34,36,36,38,38,40,40,42,42,44,44,46,46,48,48,50,50,52,52,54,54,56,56,58,58,60,60,62,62,64,64,66,66,68,68,70,70,72,72,74,74,76,76,78,78,80,80,82,82,84,84,86,86,88,88,90,90,92,92,94,94,96,96,98,98,100,100,102,102,104,104,106,106,108,108,110,110,112,112,114,114,116,116,118,118,120,120,122,122,124,124,126,126,128,128,130,130,132,132,134,134,136,136,138,138,140,140,142,142,144,144,146,146,148,148,150,0,150],"width":346,"height":249}},"shenhaijujing_tanshi":{"shenhaijujing_tanshi":{"x":-76.95,"y":-21.38,"width":139,"height":197}}}},"animations":{"H5_shenhaijujing":{"slots":{"H5_shenhaijujing_gg1":{"color":[{"time":0,"color":"ffffff01"},{"time":0.1333,"color":"ffffffcb"},{"time":0.5,"color":"ffffffff"},{"time":0.8667,"color":"ffffff00","curve":"stepped"},{"time":1,"color":"ffffff00"}]},"H5_shenhaijujing_gg2":{"color":[{"time":0,"color":"ffffff00"},{"time":0.5,"color":"ffffffff"},{"time":1,"color":"ffffff00"}]},"H5_shenhaijujing_gg3":{"color":[{"time":0,"color":"ffffff00"},{"time":0.4,"color":"ffffffff"},{"time":0.8333,"color":"ffffff00"}]},"H5_shenhaijujing_gg4":{"color":[{"time":0,"color":"ffffff00"},{"time":0.2,"color":"ffffffa1"},{"time":0.4,"color":"ffffffff"},{"time":0.8333,"color":"ffffff00"}]},"H5_shenhaijujing_gg5":{"color":[{"time":0,"color":"ffffff00"},{"time":0.3333,"color":"fffffffa"},{"time":0.8333,"color":"ffffff00"}]},"shenhaijujin_0003":{"color":[{"time":0,"color":"ffffff71"},{"time":0.9333,"color":"ffffff78"},{"time":1.3667,"color":"ffffff00"}],"attachment":[{"time":0,"name":"shenhaijujin_0003"},{"time":0.0667,"name":"shenhaijujin_0004"},{"time":0.1333,"name":"shenhaijujin_0005"},{"time":0.2,"name":"shenhaijujin_0006"},{"time":0.2667,"name":"shenhaijujin_0007"},{"time":0.3333,"name":"shenhaijujin_0008"},{"time":0.4,"name":"shenhaijujin_0009"},{"time":0.4667,"name":"shenhaijujin_0010"},{"time":0.5333,"name":"shenhaijujin_0011"},{"time":0.6,"name":"shenhaijujin_0012"},{"time":0.6667,"name":"shenhaijujin_0013"},{"time":0.7333,"name":"shenhaijujin_0014"},{"time":0.8,"name":"shenhaijujin_0015"},{"time":0.8667,"name":"shenhaijujin_0016"},{"time":0.9333,"name":"shenhaijujin_0017"},{"time":1.3667,"name":"shenhaijujin_0017"}]},"shenhaijujing_pp":{"color":[{"time":0,"color":"fffffff8"},{"time":3,"color":"ffffff00"},{"time":3.0333,"color":"ffffff08"},{"time":3.3333,"color":"fffffff6"}]},"shenhaijujing_pp2":{"color":[{"time":0,"color":"fffffffd"},{"time":1.3333,"color":"ffffff00"},{"time":1.3667,"color":"ffffff03"},{"time":3.3333,"color":"fffffffd"}]},"shenhaijujing_pp3":{"color":[{"time":0,"color":"ffffffda"},{"time":0.3333,"color":"ffffff00"},{"time":0.3667,"color":"ffffff04"},{"time":3.3333,"color":"ffffffda"}]},"shenhaijujing_pp4":{"color":[{"time":0,"color":"fffffffb"},{"time":2.1667,"color":"ffffff00"},{"time":2.2,"color":"ffffff08"},{"time":3.3333,"color":"fffffffb"}]}},"bones":{"shanhu2":{"rotate":[{"time":0,"angle":0,"curve":[0.25,0,0.75,1]},{"time":1.6667,"angle":2.51,"curve":[0.25,0,0.75,1]},{"time":3.3333,"angle":0}],"translate":[{"time":0,"x":0,"y":0,"curve":"stepped"},{"time":3.3333,"x":0,"y":0}],"scale":[{"time":0,"x":1,"y":1,"curve":"stepped"},{"time":3.3333,"x":1,"y":1}],"shear":[{"time":0,"x":0,"y":0,"curve":"stepped"},{"time":3.3333,"x":0,"y":0}]},"shanhu1":{"rotate":[{"time":0,"angle":0,"curve":[0.25,0,0.75,1]},{"time":1.6667,"angle":-3.66,"curve":[0.25,0,0.75,1]},{"time":3.3333,"angle":0}],"translate":[{"time":0,"x":0,"y":0,"curve":"stepped"},{"time":1.6667,"x":0,"y":0,"curve":"stepped"},{"time":3.3333,"x":0,"y":0}],"scale":[{"time":0,"x":1,"y":1,"curve":"stepped"},{"time":1.6667,"x":1,"y":1,"curve":"stepped"},{"time":3.3333,"x":1,"y":1}],"shear":[{"time":0,"x":0,"y":0,"curve":"stepped"},{"time":1.6667,"x":0,"y":0,"curve":"stepped"},{"time":3.3333,"x":0,"y":0}]},"bone2":{"rotate":[{"time":0,"angle":0,"curve":"stepped"},{"time":3.3333,"angle":0}],"translate":[{"time":0,"x":0,"y":0,"curve":"stepped"},{"time":3.3333,"x":0,"y":0}],"scale":[{"time":0,"x":1,"y":1,"curve":"stepped"},{"time":3.3333,"x":1,"y":1}],"shear":[{"time":0,"x":0,"y":0,"curve":"stepped"},{"time":3.3333,"x":0,"y":0}]},"bone3":{"rotate":[{"time":0,"angle":0,"curve":"stepped"},{"time":3.3333,"angle":0}],"translate":[{"time":0,"x":0,"y":0,"curve":"stepped"},{"time":3.3333,"x":0,"y":0}],"scale":[{"time":0,"x":1,"y":1,"curve":"stepped"},{"time":3.3333,"x":1,"y":1}],"shear":[{"time":0,"x":0,"y":0,"curve":"stepped"},{"time":3.3333,"x":0,"y":0}]},"bone4":{"rotate":[{"time":0,"angle":6.55,"curve":"stepped"},{"time":3.3333,"angle":6.55}],"translate":[{"time":0,"x":0,"y":0,"curve":"stepped"},{"time":3.3333,"x":0,"y":0}],"scale":[{"time":0,"x":1,"y":1,"curve":"stepped"},{"time":3.3333,"x":1,"y":1}],"shear":[{"time":0,"x":0,"y":0,"curve":"stepped"},{"time":3.3333,"x":0,"y":0}]},"bone":{"rotate":[{"time":0,"angle":0,"curve":"stepped"},{"time":1.6667,"angle":0,"curve":"stepped"},{"time":3.3333,"angle":0}],"translate":[{"time":0,"x":0,"y":0,"curve":[0.25,0,0.75,1]},{"time":1.6667,"x":0,"y":8.13,"curve":[0.25,0,0.75,1]},{"time":3.3333,"x":0,"y":0}],"scale":[{"time":0,"x":1,"y":1,"curve":"stepped"},{"time":1.6667,"x":1,"y":1,"curve":"stepped"},{"time":3.3333,"x":1,"y":1}],"shear":[{"time":0,"x":0,"y":0,"curve":"stepped"},{"time":1.6667,"x":0,"y":0,"curve":"stepped"},{"time":3.3333,"x":0,"y":0}]},"beike2":{"rotate":[{"time":0,"angle":0,"curve":"stepped"},{"time":1.6667,"angle":0,"curve":"stepped"},{"time":3.3333,"angle":0}],"translate":[{"time":0,"x":0,"y":0,"curve":"stepped"},{"time":1.6667,"x":0,"y":0,"curve":"stepped"},{"time":3.3333,"x":0,"y":0}],"scale":[{"time":0,"x":1,"y":1,"curve":[0.25,0,0.75,1]},{"time":1.6667,"x":0.889,"y":1,"curve":[0.25,0,0.75,1]},{"time":3.3333,"x":1,"y":1}],"shear":[{"time":0,"x":0,"y":0,"curve":"stepped"},{"time":1.6667,"x":0,"y":0,"curve":"stepped"},{"time":3.3333,"x":0,"y":0}]},"bone14":{"rotate":[{"time":0,"angle":0,"curve":[0.129,0.16,0.75,1]},{"time":0.6667,"angle":-3.83,"curve":[0.25,0,0.75,1]},{"time":2.6667,"angle":363.56,"curve":[0.25,0,0.91,0.89]},{"time":3.3333,"angle":0}],"translate":[{"time":0,"x":0,"y":0,"curve":"stepped"},{"time":3.3333,"x":0,"y":0}],"scale":[{"time":0,"x":1,"y":1,"curve":"stepped"},{"time":3.3333,"x":1,"y":1}],"shear":[{"time":0,"x":0,"y":0,"curve":"stepped"},{"time":3.3333,"x":0,"y":0}]},"bone15":{"rotate":[{"time":0,"angle":359.14,"curve":[0.25,0,0.75,1]},{"time":1,"angle":343.29,"curve":[0.25,0,0.75,1]},{"time":3.3333,"angle":359.14}],"translate":[{"time":0,"x":0,"y":0,"curve":"stepped"},{"time":3.3333,"x":0,"y":0}],"scale":[{"time":0,"x":1,"y":1,"curve":"stepped"},{"time":3.3333,"x":1,"y":1}],"shear":[{"time":0,"x":0,"y":0,"curve":"stepped"},{"time":3.3333,"x":0,"y":0}]},"bone16":{"rotate":[{"time":0,"angle":359.98},{"time":1.3333,"angle":342.5},{"time":1.9667,"angle":-19.27},{"time":3.3333,"angle":359.98}],"translate":[{"time":0,"x":0,"y":0,"curve":"stepped"},{"time":3.3333,"x":0,"y":0}],"scale":[{"time":0,"x":1,"y":1,"curve":"stepped"},{"time":3.3333,"x":1,"y":1}],"shear":[{"time":0,"x":0,"y":0,"curve":"stepped"},{"time":3.3333,"x":0,"y":0}]},"bone13":{"rotate":[{"time":0,"angle":359.53,"curve":[0.152,0.2,0.75,1]},{"time":0.6667,"angle":354.53,"curve":[0.25,0,0.75,1]},{"time":2.6667,"angle":364.53,"curve":[0.25,0,0.926,0.9]},{"time":3.3333,"angle":359.53}],"translate":[{"time":0,"x":0,"y":0,"curve":"stepped"},{"time":3.3333,"x":0,"y":0}],"scale":[{"time":0,"x":1,"y":1,"curve":[0.25,0,0.75,1]},{"time":1.6667,"x":0.977,"y":0.905,"curve":[0.25,0,0.75,1]},{"time":3.3333,"x":1,"y":1}],"shear":[{"time":0,"x":0,"y":0,"curve":"stepped"},{"time":3.3333,"x":0,"y":0}]},"bone17":{"rotate":[{"time":0,"angle":-0.14,"curve":[0.2,0.26,0.763,1.01]},{"time":0.6667,"angle":5.86,"curve":[0.306,0.24,0.694,0.76]},{"time":2.6667,"angle":-6.14,"curve":[0.268,0,0.88,0.92]},{"time":3.3333,"angle":-0.14}],"translate":[{"time":0,"x":0,"y":0,"curve":"stepped"},{"time":3.3333,"x":0,"y":0}],"scale":[{"time":0,"x":1,"y":1},{"time":1.6667,"x":1.019,"y":0.923},{"time":3.3333,"x":1,"y":1}],"shear":[{"time":0,"x":0,"y":0,"curve":"stepped"},{"time":3.3333,"x":0,"y":0}]},"bone18":{"rotate":[{"time":0,"angle":359.94,"curve":[0.269,0.27,0.607,0.61]},{"time":0.8333,"angle":9.79,"curve":[0.26,0.27,0.608,0.62]},{"time":3.3333,"angle":359.94}],"translate":[{"time":0,"x":0,"y":0,"curve":"stepped"},{"time":3.3333,"x":0,"y":0}],"scale":[{"time":0,"x":1,"y":1,"curve":"stepped"},{"time":3.3333,"x":1,"y":1}],"shear":[{"time":0,"x":0,"y":0,"curve":"stepped"},{"time":3.3333,"x":0,"y":0}]},"bone19":{"rotate":[{"time":0,"angle":-12.88,"curve":[0.269,0,0.618,0.42]},{"time":1,"angle":-1.38,"curve":[0.32,0.29,0.666,0.66]},{"time":2,"angle":5.41,"curve":[0.381,0.54,0.743,1]},{"time":3.3333,"angle":-12.88}],"translate":[{"time":0,"x":0,"y":0,"curve":"stepped"},{"time":3.3333,"x":0,"y":0}],"scale":[{"time":0,"x":1,"y":1,"curve":"stepped"},{"time":3.3333,"x":1,"y":1}],"shear":[{"time":0,"x":0,"y":0,"curve":"stepped"},{"time":3.3333,"x":0,"y":0}]},"bone6":{"rotate":[{"time":0,"angle":0.27,"curve":[0.148,0.18,0.75,1]},{"time":1,"angle":-5.73,"curve":[0.25,0,0.75,1]},{"time":2.6667,"angle":8.27,"curve":[0.25,0,0.897,0.86]},{"time":3.3333,"angle":0.27}],"translate":[{"time":0,"x":0,"y":0,"curve":"stepped"},{"time":3.3333,"x":0,"y":0}],"scale":[{"time":0,"x":1,"y":1,"curve":"stepped"},{"time":3.3333,"x":1,"y":1}],"shear":[{"time":0,"x":0,"y":0,"curve":"stepped"},{"time":3.3333,"x":0,"y":0}]},"bone7":{"rotate":[{"time":0,"angle":-0.19,"curve":[0.192,0.24,0.75,1]},{"time":1.0333,"angle":-12.93,"curve":[0.25,0,0.75,1]},{"time":3.3333,"angle":-0.19}],"translate":[{"time":0,"x":0,"y":0,"curve":"stepped"},{"time":3.3333,"x":0,"y":0}],"scale":[{"time":0,"x":1,"y":1,"curve":"stepped"},{"time":3.3333,"x":1,"y":1}],"shear":[{"time":0,"x":0,"y":0,"curve":"stepped"},{"time":3.3333,"x":0,"y":0}]},"bone8":{"rotate":[{"time":0,"angle":0.17},{"time":1.0333,"angle":-3.73},{"time":3.3333,"angle":0.17}],"scale":[{"time":0,"x":1,"y":1,"curve":"stepped"},{"time":3.3333,"x":1,"y":1}]},"bone9":{"rotate":[{"time":0,"angle":0},{"time":0.9667,"angle":-13.9},{"time":2.4,"angle":8.26},{"time":3.3333,"angle":0}],"translate":[{"time":0,"x":0,"y":0,"curve":"stepped"},{"time":3.3333,"x":0,"y":0}],"scale":[{"time":0,"x":1,"y":1},{"time":0.9667,"x":0.593,"y":1},{"time":3.3333,"x":1,"y":1}],"shear":[{"time":0,"x":0,"y":0,"curve":"stepped"},{"time":3.3333,"x":0,"y":0}]},"bone10":{"rotate":[{"time":0,"angle":0},{"time":1.1,"angle":-11.78},{"time":3.3333,"angle":0}]},"bone12":{"rotate":[{"time":0,"angle":0},{"time":1.0333,"angle":-13.74},{"time":3.3333,"angle":0}],"translate":[{"time":0,"x":0,"y":0,"curve":"stepped"},{"time":3.3333,"x":0,"y":0}],"scale":[{"time":0,"x":1,"y":1,"curve":"stepped"},{"time":3.3333,"x":1,"y":1}],"shear":[{"time":0,"x":0,"y":0,"curve":"stepped"},{"time":3.3333,"x":0,"y":0}]},"bone11":{"rotate":[{"time":0,"angle":0},{"time":0.9667,"angle":1.64},{"time":2.1667,"angle":10.6},{"time":3.3333,"angle":0}],"translate":[{"time":0,"x":0,"y":0,"curve":"stepped"},{"time":3.3333,"x":0,"y":0}],"scale":[{"time":0,"x":1,"y":1},{"time":0.9667,"x":1.079,"y":1},{"time":3.3333,"x":1,"y":1}],"shear":[{"time":0,"x":0,"y":0,"curve":"stepped"},{"time":3.3333,"x":0,"y":0}]},"bone5":{"rotate":[{"time":0,"angle":0,"curve":[0.09,0.12,0.75,1]},{"time":0.6667,"angle":-4,"curve":[0.25,0,0.75,1]},{"time":2.8333,"angle":4,"curve":[0.25,0,0.897,0.86]},{"time":3.3333,"angle":0}],"translate":[{"time":0,"x":0,"y":0,"curve":"stepped"},{"time":3.3333,"x":0,"y":0}],"scale":[{"time":0,"x":1,"y":1,"curve":"stepped"},{"time":3.3333,"x":1,"y":1}],"shear":[{"time":0,"x":0,"y":0,"curve":"stepped"},{"time":3.3333,"x":0,"y":0}]},"bone20":{"rotate":[{"time":0,"angle":0,"curve":"stepped"},{"time":3.3333,"angle":0}],"translate":[{"time":0,"x":10.03,"y":5.43},{"time":3,"x":10.03,"y":79.42},{"time":3.0333,"x":10.03,"y":-4.05},{"time":3.3333,"x":10.03,"y":5.43}],"scale":[{"time":0,"x":1,"y":1},{"time":3,"x":1.2,"y":1.2},{"time":3.3333,"x":1,"y":1}],"shear":[{"time":0,"x":0,"y":0,"curve":"stepped"},{"time":3.3333,"x":0,"y":0}]},"bone21":{"rotate":[{"time":0,"angle":0,"curve":"stepped"},{"time":3.3333,"angle":0}],"translate":[{"time":0,"x":0,"y":49.74},{"time":1.3333,"x":0,"y":100.32},{"time":1.3667,"x":0,"y":-3.77},{"time":3.3333,"x":0,"y":49.74}],"scale":[{"time":0,"x":0.55,"y":0.55},{"time":1.3667,"x":0.5,"y":0.5},{"time":3.3333,"x":0.55,"y":0.55}],"shear":[{"time":0,"x":0,"y":0,"curve":"stepped"},{"time":3.3333,"x":0,"y":0}]},"bone22":{"rotate":[{"time":0,"angle":0,"curve":"stepped"},{"time":3.3333,"angle":0}],"translate":[{"time":0,"x":-29.68,"y":84.02},{"time":0.3333,"x":-29.68,"y":94.47},{"time":0.3667,"x":-29.68,"y":18.69},{"time":3.3333,"x":-29.68,"y":84.02}],"scale":[{"time":0,"x":1.2,"y":1.2,"curve":"stepped"},{"time":3.3333,"x":1.2,"y":1.2}],"shear":[{"time":0,"x":0,"y":0,"curve":"stepped"},{"time":3.3333,"x":0,"y":0}]},"bone23":{"rotate":[{"time":0,"angle":0,"curve":"stepped"},{"time":3.3333,"angle":0}],"translate":[{"time":0,"x":-4.6,"y":32.92},{"time":2.1667,"x":-1.7,"y":127.59},{"time":2.2,"x":-1.66,"y":23.37},{"time":3.3333,"x":0,"y":0}],"scale":[{"time":0,"x":0.6,"y":0.6,"curve":"stepped"},{"time":3.3333,"x":0.6,"y":0.6}],"shear":[{"time":0,"x":0,"y":0,"curve":"stepped"},{"time":3.3333,"x":0,"y":0}]},"bone24":{"rotate":[{"time":0,"angle":0,"curve":"stepped"},{"time":3.3333,"angle":0}],"translate":[{"time":0,"x":0,"y":0,"curve":[0.25,0,0.75,1]},{"time":1.6667,"x":0,"y":-5.82,"curve":[0.25,0,0.75,1]},{"time":3.3333,"x":0,"y":0}],"scale":[{"time":0,"x":1,"y":1,"curve":"stepped"},{"time":3.3333,"x":1,"y":1}],"shear":[{"time":0,"x":0,"y":0,"curve":"stepped"},{"time":3.3333,"x":0,"y":0}]},"bone25":{"rotate":[{"time":0,"angle":0,"curve":"stepped"},{"time":3.3333,"angle":0}],"translate":[{"time":0,"x":0,"y":0,"curve":[0.25,0,0.911,0.87]},{"time":1.5,"x":0,"y":2.18,"curve":[0.25,0,0.75,1]},{"time":3.3333,"x":0,"y":0}],"scale":[{"time":0,"x":1,"y":1,"curve":"stepped"},{"time":3.3333,"x":1,"y":1}],"shear":[{"time":0,"x":0,"y":0,"curve":"stepped"},{"time":3.3333,"x":0,"y":0}]},"bone26":{"rotate":[{"time":0,"angle":0,"curve":"stepped"},{"time":3.3333,"angle":0}],"translate":[{"time":0,"x":0,"y":0,"curve":[0.25,0,0.75,1]},{"time":1.6667,"x":0,"y":5.09,"curve":[0.25,0,0.75,1]},{"time":3.3333,"x":0,"y":0}],"scale":[{"time":0,"x":1,"y":1,"curve":"stepped"},{"time":3.3333,"x":1,"y":1}],"shear":[{"time":0,"x":0,"y":0,"curve":"stepped"},{"time":3.3333,"x":0,"y":0}]},"bone27":{"rotate":[{"time":0,"angle":0,"curve":"stepped"},{"time":3.3333,"angle":0}],"translate":[{"time":0,"x":0,"y":0,"curve":[0.25,0,0.75,1]},{"time":1.6667,"x":0,"y":-4.36,"curve":[0.25,0,0.75,1]},{"time":3.3333,"x":0,"y":0}],"scale":[{"time":0,"x":1,"y":1,"curve":"stepped"},{"time":3.3333,"x":1,"y":1}],"shear":[{"time":0,"x":0,"y":0,"curve":"stepped"},{"time":3.3333,"x":0,"y":0}]},"bone28":{"rotate":[{"time":0,"angle":0,"curve":"stepped"},{"time":3.3333,"angle":0}],"translate":[{"time":0,"x":0,"y":0,"curve":"stepped"},{"time":3.3333,"x":0,"y":0}],"scale":[{"time":0,"x":1,"y":1,"curve":"stepped"},{"time":3.3333,"x":1,"y":1}],"shear":[{"time":0,"x":0,"y":0,"curve":"stepped"},{"time":3.3333,"x":0,"y":0}]},"bone29":{"rotate":[{"time":0,"angle":0,"curve":"stepped"},{"time":0.5,"angle":0,"curve":"stepped"},{"time":1,"angle":0}],"translate":[{"time":0,"x":-6.06,"y":0.01},{"time":0.5,"x":28.69,"y":-16.34},{"time":1,"x":51.56,"y":-47.19}],"scale":[{"time":0,"x":1,"y":1},{"time":0.5,"x":1.358,"y":1},{"time":1,"x":1,"y":1}],"shear":[{"time":0,"x":0,"y":0,"curve":"stepped"},{"time":0.5,"x":0,"y":0,"curve":"stepped"},{"time":1,"x":0,"y":0}]},"bone30":{"rotate":[{"time":0,"angle":0,"curve":"stepped"},{"time":0.5,"angle":0,"curve":"stepped"},{"time":1,"angle":0}],"translate":[{"time":0,"x":-5.57,"y":4.56},{"time":0.5,"x":1.43,"y":-10.94},{"time":1,"x":8.43,"y":-26.45}],"scale":[{"time":0,"x":1,"y":1,"curve":"stepped"},{"time":0.5,"x":1,"y":1,"curve":"stepped"},{"time":1,"x":1,"y":1}],"shear":[{"time":0,"x":0,"y":0,"curve":"stepped"},{"time":0.5,"x":0,"y":0,"curve":"stepped"},{"time":1,"x":0,"y":0}]},"bone32":{"translate":[{"time":0,"x":-0.58,"y":0.48},{"time":0.8333,"x":14.02,"y":-11.49}]},"bone31":{"rotate":[{"time":0,"angle":-34.52}],"translate":[{"time":0,"x":7.08,"y":2.02},{"time":0.8333,"x":9.65,"y":-22.68}],"scale":[{"time":0,"x":1,"y":1}],"shear":[{"time":0,"x":0,"y":0}]},"bone33":{"rotate":[{"time":0,"angle":-46.07}],"translate":[{"time":0,"x":7.16,"y":4.63},{"time":0.8333,"x":5.53,"y":-30.77}]}},"deform":{"default":{"H5_shenhaijujing_gg1":{"H5_shenhaijujing_gg1":[{"time":0,"vertices":[11.79453,-3.65524,-0.21561,5.8E-4,-0.93372,2.92542,13.02356,1.21683,-2.54703,5.36465,0.12903,6.4E-4,7.09738,-13.65494,7.5813,0.00259,0.24521]},{"time":0.1333,"vertices":[7.83858,-6.61328,-0.87297,0.42005,-0.53494,2.14395,11.75421,-2.12468,-1.56755,-4.02689,-0.07268,-3.26441,7.35308,-13.10963,3.56266,-5.10308,-0.94348,-2.2596]},{"time":0.2,"vertices":[5.86427,-8.09431,-1.19877,0.62919,-0.33286,1.75486,11.1194,-3.79241,-1.0811,-8.7211,-0.17692,-4.89758,7.47864,-12.83903,1.55352,-7.65839,-1.53801,-3.39052]},{"time":0.3333,"vertices":[1.90932,-11.05284,-1.85527,1.04848,0.06667,0.97387,9.8499,-7.13297,0.67244,-4.8155,7.07526,-4.79799,17.22182,-21.97141,-2.46517,-12.7647,-2.72681,-5.65097]},{"time":0.5,"vertices":[-3.02873,-14.75458,-2.67232,1.57198,0.56972,6.6E-4,8.26303,-11.304,-0.19078,-14.12929,-0.63805,-12.245,8.04823,-11.61603,-7.48758,-19.15192,-4.21315,-8.47757]},{"time":0.6333,"vertices":[-5.34085,3.08137,-2.56359,8.95826,3.45418,15.88796,7.76596,-1.15307,-2.01048,-17.28793,5.74932,-6.34306,10.52922,-7.67934,-5.64963,-12.50902,-3.89295,-5.88985]},{"time":0.7333,"vertices":[-7.07249,13.35406,-2.48018,14.49755,5.61849,27.80643,7.3924,6.46365,-3.37777,-19.65462,2.04186,-15.56002,13.69184,-19.61175,-4.27042,-7.53043,-3.65297,-3.94981]},{"time":0.8333,"vertices":[4.10606,23.94111,1.73798,28.90508,-3.9638,30.13502,9.56851,4.39344,-4.74038,-14.40958,0.06439,-10.78379,11.40293,-12.25603,-2.3522,-1.86921,-2.19094,-2.46814]},{"time":1,"vertices":[7.5791,9.8E-4,-0.21335,-3.0E-5,-7.58356,-0.00101,-7.58133,-0.00101,-7.5791,-0.00101,0.12683,0,7.58359,9.8E-4,7.58133,9.8E-4,0.24521]}]},"H5_shenhaijujing_gg2":{"H5_shenhaijujing_gg1":[{"time":0,"vertices":[1.84595,24.1005,-4.31906,17.14662,-6.7872,-0.00241,-7.39877,-1.39259,-2.46384,-20.3928,2.77823,-4.17072,8.32669,-5.09503,4.62411,8.80767]},{"time":0.2333,"vertices":[5.76995,33.51694,-8.11483,21.50661,-14.34512,10.00133,-3.08784,0.11893,-10.72145,-11.97393,1.51467,-4.25643,4.24212,-2.60666,-2.67371,10.12621,-3.61337,10.65785]},{"time":0.5,"vertices":[6.43314,21.28075,-6.23734,13.68919,-18.67691,10.65477,-10.10857,-3.90334,-10.59338,-16.0068,0.07256,-2.91769,3.79128,7.72763,-11.01385,11.63348,-9.17419,8.46511]},{"time":0.7333,"vertices":[1.52526,27.29963,-8.8956,22.55954,-22.18036,19.30749,-18.67381,-2.29289,-19.35453,-20.54101,-4.58845,-8.89479,5.43738,4.83338,-8.29006,17.48323,-11.31699,8.61091]},{"time":1,"vertices":[-2.74368,38.20907,-14.12305,28.74605,-29.31308,23.822,-28.46286,-0.45334,-29.36627,-25.72395,-10.35928,-21.10002,4.99026,-6.03482,-5.17783,24.17,-13.76566,8.77781]}]},"H5_shenhaijujing_gg3":{"H5_shenhaijujing_gg1":[{"time":0,"vertices":[2.90335,17.37761,-11.54144,14.48679,-26.53336,13.35918,-26.51764,-6.44159,-22.63013,-23.4062,-8.07681,-25.83923,4.8866,-28.75217,2.9288,-3.57634,-10.94458,-4.32397]},{"time":0.4,"vertices":[-13.66956,20.83733,-11.54349,14.48654,-22.58746,14.33202,-18.04037,-9.72136,-18.13956,-22.79546,-7.47586,-9.37927,-1.66055,-17.71544,-13.82977,7.07159,-18.9404,4.11592]},{"time":0.8333,"vertices":[-9.84259,22.07446,-25.39584,17.64758,-38.09586,17.72337,-34.99582,-9.38068,-33.38635,-34.91919,-15.38947,-26.79767,-4.97272,-16.79997,-8.25824,5.06157,-18.94034,4.11598]}]},"H5_shenhaijujing_gg4":{"H5_shenhaijujing_gg1":[{"time":0,"vertices":[11.90863,24.3928,6.07715,4.57297,-5.32751,35.05871,-2.02927,19.0524,-6.33466,-0.00226,0.00363,3.9E-4,9.63458,-4.19008,13.9415,12.95969,1.5202,9.90887]},{"time":0.2,"vertices":[7.78775,23.34571,0.68721,4.28703,-9.00417,33.43816,-5.64158,17.52688,-9.62898,-0.95584,-2.27652,5.5E-4,6.72012,-3.99853,11.40655,13.24618,0.18932,9.62304]},{"time":0.4,"vertices":[-4.57074,20.20073,-15.47272,3.42976,-20.0329,28.58012,-16.48157,12.95492,-19.51831,-3.81316,-9.12357,3.9E-4,-2.02875,-3.42789,3.80011,14.10303,-3.80405,8.76555]},{"time":0.8333,"vertices":[-1.27798,32.39651,-11.16736,34.29848,-25.83612,35.42014,-25.49686,13.89211,-25.05286,-8.77816,-9.37869,-7.62245,-1.52103,-0.75959,3.80038,14.10332,-11.5946,13.80356]}]},"H5_shenhaijujing_gg5":{"H5_shenhaijujing_gg1":[{"time":0,"vertices":[2.77296,20.45752,-4.02557,15.70937,-16.74303,12.47343,-16.27773,0.97928,-17.57152,-23.02979,-7.71147,-20.83287,3.89308,-17.86766,2.86954,0.08324,-5.23375,-2.30406]},{"time":0.3333,"vertices":[-9.21021,22.27621,-6.84221,11.3114,-11.87018,18.12222,-9.11946,2.37735,-19.0262,-8.68979,-12.63715,-9.46599,-8.45065,-12.70265,-7.68184,2.18216,-12.2959,1.33147]},{"time":0.4333,"vertices":[-9.92187,23.0248,-11.05661,14.11721,-17.72649,19.63414,-15.07124,1.39301,-23.18776,-12.4521,-13.83881,-4.99287,-15.21826,-12.0281,-9.77003,3.41938,-15.58378,1.57463]},{"time":0.6333,"vertices":[-8.40939,19.32781,-20.62,21.3753,-30.42985,25.50868,-26.97517,-0.57328,-31.51344,-19.97557,-21.5433,-6.02524,-9.4787,-2.82913,-17.20034,11.07411,-22.15977,2.06048]},{"time":0.8333,"vertices":[-12.7652,26.01273,-27.90764,25.34152,-41.14719,25.68777,-38.87819,-2.53723,-39.8398,-27.49736,-23.01923,-20.78653,-9.54407,-14.41075,-18.1234,8.36177,-28.73532,2.5462]}]},"shenhaijujing_shenti":{"shenhaijujing_shenti":[{"time":0},{"time":0.2333,"offset":530,"vertices":[-3.57032,2.29147,-5.19731,6.93905,-5.4508,4.82757,-3.11429,2.55138,0.71367,-1.91876,2.48241,-2.03366,1.41563,-1.15973,0,0,-4.15541,5.66402]},{"time":0.4667,"offset":540,"vertices":[-0.32023,0.26236]}]}}}}}}