{"skeleton":{"hash":"fHIVnkNAfQyE7am49Ujsb25DK2E","spine":"3.6.53","width":1457,"height":815.66,"images":"./images/"},"bones":[{"name":"root"},{"name":"zzzzz","parent":"root"},{"name":"lizi","parent":"zzzzz","x":-237.22,"y":272.19},{"name":"lizi2","parent":"zzzzz","x":-237.22,"y":258.7},{"name":"lizi3","parent":"zzzzz","x":-270.48,"y":241.62},{"name":"lizi4","parent":"zzzzz","x":-237.22,"y":272.19},{"name":"zzzzz2","parent":"zzzzz","x":-494.54,"y":-159.92},{"name":"zzzzz3","parent":"zzzzz","x":-658.28,"y":-250.1},{"name":"zzzzz4","parent":"zzzzz","x":-318.94,"y":-119.58},{"name":"zzzzz5","parent":"zzzzz","x":-417,"y":257.17},{"name":"zzzzz6","parent":"zzzzz","x":-417,"y":257.17}],"slots":[{"name":"H5_yinhang_BG","bone":"zzzzz","attachment":"H5_yinhang_BG"},{"name":"H5_yinhang_xia","bone":"zzzzz2","attachment":"H5_yinhang_xia"},{"name":"H5_yinhang_jinbi02","bone":"zzzzz3","attachment":"H5_yinhang_jinbi02"},{"name":"H5_yinhang_jinbi01","bone":"zzzzz4","attachment":"H5_yinhang_jinbi01"},{"name":"lizi_50","bone":"lizi","attachment":"lizi_59"},{"name":"lizi_52","bone":"lizi3","attachment":"lizi_59"},{"name":"lizi_51","bone":"lizi2","attachment":"lizi_59"},{"name":"lizi_53","bone":"lizi4","attachment":"lizi_59"},{"name":"H5_yinhang_biaoti","bone":"zzzzz5","attachment":"H5_yinhang_biaoti"},{"name":"H5_yinhang_biaoti2","bone":"zzzzz6","attachment":"H5_yinhang_biaoti","blend":"additive"}],"skins":{"default":{"H5_yinhang_BG":{"H5_yinhang_BG":{"x":-4,"y":-38,"width":1376,"height":668}},"H5_yinhang_biaoti":{"H5_yinhang_biaoti":{"x":-8,"y":58.48,"width":696,"height":240}},"H5_yinhang_biaoti2":{"H5_yinhang_biaoti":{"x":-8,"y":58.48,"width":696,"height":240}},"H5_yinhang_jinbi01":{"H5_yinhang_jinbi01":{"x":-1.06,"y":-6.92,"width":134,"height":69}},"H5_yinhang_jinbi02":{"H5_yinhang_jinbi02":{"x":5.78,"y":-4.4,"width":95,"height":59}},"H5_yinhang_xia":{"H5_yinhang_xia":{"x":-25.96,"y":67.92,"width":469,"height":576}},"lizi_50":{"lizi_50":{"x":71.57,"y":38.34,"width":190,"height":164},"lizi_51":{"x":71.57,"y":38.34,"width":190,"height":164},"lizi_52":{"x":71.57,"y":38.34,"width":190,"height":164},"lizi_53":{"x":71.57,"y":38.34,"width":190,"height":164},"lizi_54":{"x":71.57,"y":38.34,"width":190,"height":164},"lizi_55":{"x":71.57,"y":38.34,"width":190,"height":164},"lizi_56":{"x":71.57,"y":38.34,"width":190,"height":164},"lizi_57":{"x":71.57,"y":38.34,"width":190,"height":164},"lizi_58":{"x":71.57,"y":38.34,"width":190,"height":164},"lizi_59":{"x":71.57,"y":38.34,"width":190,"height":164}},"lizi_51":{"lizi_50":{"x":71.57,"y":38.34,"width":190,"height":164},"lizi_51":{"x":71.57,"y":38.34,"width":190,"height":164},"lizi_52":{"x":71.57,"y":38.34,"width":190,"height":164},"lizi_53":{"x":71.57,"y":38.34,"width":190,"height":164},"lizi_54":{"x":71.57,"y":38.34,"width":190,"height":164},"lizi_55":{"x":71.57,"y":38.34,"width":190,"height":164},"lizi_56":{"x":71.57,"y":38.34,"width":190,"height":164},"lizi_57":{"x":71.57,"y":38.34,"width":190,"height":164},"lizi_58":{"x":71.57,"y":38.34,"width":190,"height":164},"lizi_59":{"x":71.57,"y":38.34,"width":190,"height":164}},"lizi_52":{"lizi_50":{"x":71.57,"y":38.34,"width":190,"height":164},"lizi_51":{"x":71.57,"y":38.34,"width":190,"height":164},"lizi_52":{"x":71.57,"y":38.34,"width":190,"height":164},"lizi_53":{"x":71.57,"y":38.34,"width":190,"height":164},"lizi_54":{"x":71.57,"y":38.34,"width":190,"height":164},"lizi_55":{"x":71.57,"y":38.34,"width":190,"height":164},"lizi_56":{"x":71.57,"y":38.34,"width":190,"height":164},"lizi_57":{"x":71.57,"y":38.34,"width":190,"height":164},"lizi_58":{"x":71.57,"y":38.34,"width":190,"height":164},"lizi_59":{"x":71.57,"y":38.34,"width":190,"height":164}},"lizi_53":{"lizi_50":{"x":71.57,"y":38.34,"width":190,"height":164},"lizi_51":{"x":71.57,"y":38.34,"width":190,"height":164},"lizi_52":{"x":71.57,"y":38.34,"width":190,"height":164},"lizi_53":{"x":71.57,"y":38.34,"width":190,"height":164},"lizi_54":{"x":71.57,"y":38.34,"width":190,"height":164},"lizi_55":{"x":71.57,"y":38.34,"width":190,"height":164},"lizi_56":{"x":71.57,"y":38.34,"width":190,"height":164},"lizi_57":{"x":71.57,"y":38.34,"width":190,"height":164},"lizi_58":{"x":71.57,"y":38.34,"width":190,"height":164},"lizi_59":{"x":71.57,"y":38.34,"width":190,"height":164}}}},"animations":{"animation":{"slots":{"H5_yinhang_biaoti2":{"color":[{"time":0,"color":"ffffff60","curve":[0.25,0,0.75,1]},{"time":1.5,"color":"ffffff00","curve":[0.25,0,0.75,1]},{"time":3,"color":"ffffff60"}]},"lizi_50":{"attachment":[{"time":0,"name":"lizi_50"},{"time":0.0667,"name":"lizi_51"},{"time":0.1333,"name":"lizi_52"},{"time":0.2,"name":"lizi_53"},{"time":0.2667,"name":"lizi_54"},{"time":0.3333,"name":"lizi_55"},{"time":0.4,"name":"lizi_56"},{"time":0.4667,"name":"lizi_57"},{"time":0.5333,"name":"lizi_58"},{"time":0.6,"name":"lizi_59"},{"time":0.6667,"name":"lizi_50"},{"time":0.7333,"name":"lizi_51"},{"time":0.8,"name":"lizi_52"},{"time":0.8667,"name":"lizi_53"},{"time":0.9333,"name":"lizi_54"},{"time":1,"name":"lizi_55"},{"time":1.0667,"name":"lizi_56"},{"time":1.1333,"name":"lizi_57"},{"time":1.2,"name":"lizi_58"},{"time":1.2667,"name":"lizi_59"},{"time":1.3333,"name":"lizi_50"},{"time":1.4,"name":"lizi_51"},{"time":1.4667,"name":"lizi_52"},{"time":1.5333,"name":"lizi_53"},{"time":1.6,"name":"lizi_54"},{"time":1.6667,"name":"lizi_55"},{"time":1.7333,"name":"lizi_56"},{"time":1.8,"name":"lizi_57"},{"time":1.8667,"name":"lizi_58"},{"time":1.9333,"name":"lizi_59"},{"time":2,"name":"lizi_50"},{"time":2.0667,"name":"lizi_51"},{"time":2.1333,"name":"lizi_52"},{"time":2.2,"name":"lizi_53"},{"time":2.2667,"name":"lizi_54"},{"time":2.3333,"name":"lizi_55"},{"time":2.4,"name":"lizi_56"},{"time":2.4667,"name":"lizi_57"},{"time":2.5333,"name":"lizi_58"},{"time":2.6,"name":"lizi_59"},{"time":2.6667,"name":"lizi_50"},{"time":2.7333,"name":"lizi_52"},{"time":2.8,"name":"lizi_54"},{"time":2.8667,"name":"lizi_56"},{"time":2.9333,"name":"lizi_58"},{"time":3,"name":"lizi_50"}]},"lizi_51":{"attachment":[{"time":0,"name":"lizi_50"},{"time":0.0667,"name":"lizi_51"},{"time":0.1333,"name":"lizi_52"},{"time":0.2,"name":"lizi_53"},{"time":0.2667,"name":"lizi_54"},{"time":0.3333,"name":"lizi_55"},{"time":0.4,"name":"lizi_56"},{"time":0.4667,"name":"lizi_57"},{"time":0.5333,"name":"lizi_58"},{"time":0.6,"name":"lizi_59"},{"time":0.6667,"name":"lizi_50"},{"time":0.7333,"name":"lizi_51"},{"time":0.8,"name":"lizi_52"},{"time":0.8667,"name":"lizi_53"},{"time":0.9333,"name":"lizi_54"},{"time":1,"name":"lizi_55"},{"time":1.0667,"name":"lizi_56"},{"time":1.1333,"name":"lizi_57"},{"time":1.2,"name":"lizi_58"},{"time":1.2667,"name":"lizi_59"},{"time":1.3333,"name":"lizi_50"},{"time":1.4,"name":"lizi_51"},{"time":1.4667,"name":"lizi_52"},{"time":1.5333,"name":"lizi_53"},{"time":1.6,"name":"lizi_54"},{"time":1.6667,"name":"lizi_55"},{"time":1.7333,"name":"lizi_56"},{"time":1.8,"name":"lizi_57"},{"time":1.8667,"name":"lizi_58"},{"time":1.9333,"name":"lizi_59"},{"time":2,"name":"lizi_50"},{"time":2.0667,"name":"lizi_51"},{"time":2.1333,"name":"lizi_52"},{"time":2.2,"name":"lizi_53"},{"time":2.2667,"name":"lizi_54"},{"time":2.3333,"name":"lizi_55"},{"time":2.4,"name":"lizi_56"},{"time":2.4667,"name":"lizi_57"},{"time":2.5333,"name":"lizi_58"},{"time":2.6,"name":"lizi_59"},{"time":2.6667,"name":"lizi_50"},{"time":2.7333,"name":"lizi_52"},{"time":2.8,"name":"lizi_54"},{"time":2.8667,"name":"lizi_56"},{"time":2.9333,"name":"lizi_58"},{"time":3,"name":"lizi_50"}]},"lizi_52":{"attachment":[{"time":0,"name":"lizi_50"},{"time":0.0667,"name":"lizi_51"},{"time":0.1333,"name":"lizi_52"},{"time":0.2,"name":"lizi_53"},{"time":0.2667,"name":"lizi_54"},{"time":0.3333,"name":"lizi_55"},{"time":0.4,"name":"lizi_56"},{"time":0.4667,"name":"lizi_57"},{"time":0.5333,"name":"lizi_58"},{"time":0.6,"name":"lizi_59"},{"time":0.6667,"name":"lizi_50"},{"time":0.7333,"name":"lizi_51"},{"time":0.8,"name":"lizi_52"},{"time":0.8667,"name":"lizi_53"},{"time":0.9333,"name":"lizi_54"},{"time":1,"name":"lizi_55"},{"time":1.0667,"name":"lizi_56"},{"time":1.1333,"name":"lizi_57"},{"time":1.2,"name":"lizi_58"},{"time":1.2667,"name":"lizi_59"},{"time":1.3333,"name":"lizi_50"},{"time":1.4,"name":"lizi_51"},{"time":1.4667,"name":"lizi_52"},{"time":1.5333,"name":"lizi_53"},{"time":1.6,"name":"lizi_54"},{"time":1.6667,"name":"lizi_55"},{"time":1.7333,"name":"lizi_56"},{"time":1.8,"name":"lizi_57"},{"time":1.8667,"name":"lizi_58"},{"time":1.9333,"name":"lizi_59"},{"time":2,"name":"lizi_50"},{"time":2.0667,"name":"lizi_51"},{"time":2.1333,"name":"lizi_52"},{"time":2.2,"name":"lizi_53"},{"time":2.2667,"name":"lizi_54"},{"time":2.3333,"name":"lizi_55"},{"time":2.4,"name":"lizi_56"},{"time":2.4667,"name":"lizi_57"},{"time":2.5333,"name":"lizi_58"},{"time":2.6,"name":"lizi_59"},{"time":2.6667,"name":"lizi_50"},{"time":2.7333,"name":"lizi_52"},{"time":2.8,"name":"lizi_54"},{"time":2.8667,"name":"lizi_56"},{"time":2.9333,"name":"lizi_58"},{"time":3,"name":"lizi_50"}]},"lizi_53":{"attachment":[{"time":0,"name":"lizi_50"},{"time":0.0667,"name":"lizi_51"},{"time":0.1333,"name":"lizi_52"},{"time":0.2,"name":"lizi_53"},{"time":0.2667,"name":"lizi_54"},{"time":0.3333,"name":"lizi_55"},{"time":0.4,"name":"lizi_56"},{"time":0.4667,"name":"lizi_57"},{"time":0.5333,"name":"lizi_58"},{"time":0.6,"name":"lizi_59"},{"time":0.6667,"name":"lizi_50"},{"time":0.7333,"name":"lizi_51"},{"time":0.8,"name":"lizi_52"},{"time":0.8667,"name":"lizi_53"},{"time":0.9333,"name":"lizi_54"},{"time":1,"name":"lizi_55"},{"time":1.0667,"name":"lizi_56"},{"time":1.1333,"name":"lizi_57"},{"time":1.2,"name":"lizi_58"},{"time":1.2667,"name":"lizi_59"},{"time":1.3333,"name":"lizi_50"},{"time":1.4,"name":"lizi_51"},{"time":1.4667,"name":"lizi_52"},{"time":1.5333,"name":"lizi_53"},{"time":1.6,"name":"lizi_54"},{"time":1.6667,"name":"lizi_55"},{"time":1.7333,"name":"lizi_56"},{"time":1.8,"name":"lizi_57"},{"time":1.8667,"name":"lizi_58"},{"time":1.9333,"name":"lizi_59"},{"time":2,"name":"lizi_50"},{"time":2.0667,"name":"lizi_51"},{"time":2.1333,"name":"lizi_52"},{"time":2.2,"name":"lizi_53"},{"time":2.2667,"name":"lizi_54"},{"time":2.3333,"name":"lizi_55"},{"time":2.4,"name":"lizi_56"},{"time":2.4667,"name":"lizi_57"},{"time":2.5333,"name":"lizi_58"},{"time":2.6,"name":"lizi_59"},{"time":2.6667,"name":"lizi_50"},{"time":2.7333,"name":"lizi_52"},{"time":2.8,"name":"lizi_54"},{"time":2.8667,"name":"lizi_56"},{"time":2.9333,"name":"lizi_58"},{"time":3,"name":"lizi_50"}]}},"bones":{"zzzzz2":{"translate":[{"time":0,"x":0,"y":0,"curve":[0.25,0,0.75,1]},{"time":1.1667,"x":0,"y":18.9,"curve":[0.25,0,0.75,1]},{"time":3,"x":0,"y":0}]},"lizi2":{"translate":[{"time":0,"x":-335.84,"y":6.02}],"scale":[{"time":0,"x":-1,"y":1}],"shear":[{"time":0,"x":31.19,"y":7.28}]},"zzzzz3":{"translate":[{"time":0,"x":0,"y":12.63,"curve":[0.351,0.4,0.757,1]},{"time":1,"x":0,"y":0,"curve":[0.25,0,0.75,1]},{"time":2.5,"x":0,"y":17.63,"curve":[0.265,0,0.618,0.43]},{"time":3,"x":0,"y":12.63}]},"zzzzz4":{"translate":[{"time":0,"x":0,"y":5,"curve":[0.382,0.57,0.735,1]},{"time":0.5,"x":0,"y":0,"curve":[0.25,0,0.75,1]},{"time":2,"x":0,"y":17.63,"curve":[0.243,0,0.649,0.6]},{"time":3,"x":0,"y":5}]},"lizi4":{"translate":[{"time":0,"x":-366.4,"y":-30.83}],"scale":[{"time":0,"x":-1,"y":1}],"shear":[{"time":0,"x":31.19,"y":7.28}]}}}}}